mmrlsp/__init__.py
mmrlsp/material-relative-language-selector.js
mkdocs_material_relative_language_selector-1.1.4.dist-info/LICENSE
mkdocs_material_relative_language_selector-1.1.4.dist-info/METADATA
mkdocs_material_relative_language_selector-1.1.4.dist-info/WHEEL
mkdocs_material_relative_language_selector-1.1.4.dist-info/entry_points.txt
mkdocs_material_relative_language_selector-1.1.4.dist-info/top_level.txt
mkdocs_material_relative_language_selector-1.1.4.dist-info/RECORD
