Metadata-Version: 2.1
Name: mkdocs-material-relative-language-selector
Version: 1.1.4
Summary: Relative access between translations using mkdocs-material theme.
Home-page: https://github.com/mondeja/mkdocs-material-relative-language-selector
Author: Álvaro Mondéjar Rubio
Author-email: mondejar1994@gmail.com
License: BSD-3-Clause
Platform: UNKNOWN
Classifier: License :: OSI Approved :: BSD License
Classifier: Programming Language :: Python
Classifier: Programming Language :: Python :: 3
Classifier: Programming Language :: Python :: 3 :: Only
Classifier: Programming Language :: Python :: 3.6
Classifier: Programming Language :: Python :: 3.7
Classifier: Programming Language :: Python :: 3.8
Classifier: Programming Language :: Python :: 3.9
Classifier: Programming Language :: Python :: 3.10
Classifier: Programming Language :: Python :: Implementation :: CPython
Classifier: Programming Language :: Python :: Implementation :: PyPy
Classifier: Topic :: Documentation
Classifier: Topic :: Internet
Classifier: Topic :: Internet :: WWW/HTTP :: Dynamic Content
Requires-Python: >=3.6
Provides-Extra: dev
Requires-Dist: bump2version (==1.0.1) ; extra == 'dev'
Requires-Dist: flake8 (==3.9.1) ; extra == 'dev'
Requires-Dist: flake8-implicit-str-concat (==0.2.0) ; extra == 'dev'
Requires-Dist: flake8-print (==4.0.0) ; extra == 'dev'
Requires-Dist: isort (==5.8.0) ; extra == 'dev'
Requires-Dist: pre-commit (==2.12.1) ; extra == 'dev'
